mymcp/__init__.py
mymcp/__main__.py
mymcp/cli.py
mymcp/demo.py
mymcp/server.py
mymcp/types.py
moneymcp-0.1.1.dist-info/METADATA
moneymcp-0.1.1.dist-info/WHEEL
moneymcp-0.1.1.dist-info/entry_points.txt
moneymcp-0.1.1.dist-info/top_level.txt
moneymcp-0.1.1.dist-info/RECORD
