Metadata-Version: 2.4
Name: moneymcp
Version: 0.1.1
Summary: A financial analysis MCP server that provides tools for comprehensive market data analysis
Author: easyllms
Author-email: easyllms <contract@easyllms.com>
License: MIT
Project-URL: Homepage, https://github.com/yourusername/mymcp
Project-URL: Bug Tracker, https://github.com/yourusername/mymcp/issues
Classifier: Programming Language :: Python :: 3
Classifier: License :: OSI Approved :: MIT License
Classifier: Operating System :: OS Independent
Requires-Python: >=3.8
Requires-Dist: yfinance
Requires-Dist: fastmcp
Requires-Dist: finnhub-python
Requires-Dist: fredapi
Requires-Dist: pandas
Requires-Dist: pydantic
Dynamic: author
Dynamic: requires-python
